mcp_gateway/__init__.py
mcp_gateway/config.py
mcp_gateway/sanitizers.py
mcp_gateway/server.py
mcp_gateway/plugins/__init__.py
mcp_gateway/plugins/base.py
mcp_gateway/plugins/manager.py
mcp_gateway/plugins/guardrails/__init__.py
mcp_gateway/plugins/guardrails/basic.py
mcp_gateway/plugins/guardrails/lasso.py
mcp_gateway/plugins/guardrails/presidio.py
mcp_gateway/plugins/tracing/__init__.py
mcp_gateway/plugins/tracing/xetrack.py
mseep_mcp_gateway-1.0.5.dist-info/licenses/LICENSE
tests/__init__.py
tests/simple_pii_example.py
tests/test_basic_guardrail.py
tests/test_lasso_guardrail.py
tests/test_lasso_guardrail_pii.py
tests/test_plugin_duplicates.py
tests/xetrack_tracing_test.py
mseep_mcp_gateway-1.0.5.dist-info/METADATA
mseep_mcp_gateway-1.0.5.dist-info/WHEEL
mseep_mcp_gateway-1.0.5.dist-info/top_level.txt
mseep_mcp_gateway-1.0.5.dist-info/RECORD
